sumapi/__init__.py
sumapi/api.py
sumapi/config.py
sumapi-0.4.0.dist-info/LICENSE
sumapi-0.4.0.dist-info/METADATA
sumapi-0.4.0.dist-info/WHEEL
sumapi-0.4.0.dist-info/top_level.txt
sumapi-0.4.0.dist-info/RECORD
