Metadata-Version: 2.1
Name: sumapi
Version: 0.4.0
Summary: API Library for SumAPI with Python
Home-page: https://github.com/summarify/sumapi
Author: Summarify
Author-email: info@summarify.io
License: UNKNOWN
Platform: UNKNOWN
Classifier: Programming Language :: Python :: 3
Classifier: License :: OSI Approved :: MIT License
Classifier: Operating System :: OS Independent
Requires-Python: >=3.5.5
License-File: LICENSE
Requires-Dist: requests
Requires-Dist: tqdm (==4.59.0)
